{"schema_version":"fantasy_pool_score_predictions_qf_v1","generated_at":"2026-07-08T12:35:43.868Z","source_checked":"2026-07-08","model_stage":"qf_score_prediction","data_status":"qf_score_prediction_pass","modelVersion":"score-qf-v1","model_version":"score-qf-v1","safety_labels":["Quarterfinal fantasy setup","all 8 R16 fixtures final","final QF fixtures only","ownership not used as signal","final squads not source-backed"],"input_files":["data/qfFixtureAuthority_v1.json","data/knockoutScorePredictor_v1.json"],"summary":{"fixture_prediction_count":4,"final_known_fixture_predictions":4,"partial_or_pending_fixture_rows":0,"defaultMatchday":"qf","ownershipUsedAsSignal":false,"finalSquadsSourceBacked":false,"completedR16FixturesUsed":8,"incompleteR16Fixtures":0},"fixtureScorePredictions":[{"prediction_id":"fwc2026-m097-score-qf-v1","match_id":"fwc2026-m097","fixture_id":"fwc2026-m097","match_number":97,"matchday":"QF","fantasy_matchday_id":"qf","stage":"quarterfinal","group":"QF","date":"2026-07-09T21:00:00+01:00","eastern_datetime_label":"Jul 9, 2026 · 4:00 PM ET","fixture_authority_status":"final_known","public_label":"Final","home_team_id":"france","home_team":"France","away_team_id":"morocco","away_team":"Morocco","home_expected_goals":1.809,"away_expected_goals":0.35,"home_projected_xg":1.809,"away_projected_xg":0.35,"total_expected_goals":2.159,"home_win_probability":0.7347,"draw_probability":0.201,"away_win_probability":0.0644,"home_clean_sheet_probability":0.7047,"away_clean_sheet_probability":0.1638,"both_teams_to_score_probability":0.2469,"upset_risk_probability":0.1506,"probability_extra_time":0.201,"home_advance_probability":0.8494,"away_advance_probability":0.1506,"home_advance_in_90_probability":0.7347,"away_advance_in_90_probability":0.0644,"home_advance_after_extra_time_probability":0.0466,"away_advance_after_extra_time_probability":0.0297,"home_advance_on_penalties_probability":0.0681,"away_advance_on_penalties_probability":0.0565,"favorite_team_id":"france","favorite_team":"France","favorite_win_probability":0.8494,"projected_advancing_team":"France","matchUncertainty":"Low","uncertainty_label":"Low","top_scorelines":[{"scoreline":"1-0","home_goals":1,"away_goals":0,"probability":0.2089},{"scoreline":"2-0","home_goals":2,"away_goals":0,"probability":0.1889},{"scoreline":"0-0","home_goals":0,"away_goals":0,"probability":0.1155},{"scoreline":"3-0","home_goals":3,"away_goals":0,"probability":0.1139},{"scoreline":"1-1","home_goals":1,"away_goals":1,"probability":0.0731},{"scoreline":"2-1","home_goals":2,"away_goals":1,"probability":0.0661}],"top_scoreline":"1-0","data_quality_flags":["score_prediction_qf_v1","completed_r16_only","ownership_not_used_as_signal","final_squads_not_source_backed"]},{"prediction_id":"fwc2026-m098-score-qf-v1","match_id":"fwc2026-m098","fixture_id":"fwc2026-m098","match_number":98,"matchday":"QF","fantasy_matchday_id":"qf","stage":"quarterfinal","group":"QF","date":"2026-07-10T20:00:00+01:00","eastern_datetime_label":"Jul 10, 2026 · 3:00 PM ET","fixture_authority_status":"final_known","public_label":"Final","home_team_id":"spain","home_team":"Spain","away_team_id":"belgium","away_team":"Belgium","home_expected_goals":1.971,"away_expected_goals":0.527,"home_projected_xg":1.971,"away_projected_xg":0.527,"total_expected_goals":2.498,"home_win_probability":0.7184,"draw_probability":0.1926,"away_win_probability":0.089,"home_clean_sheet_probability":0.5904,"away_clean_sheet_probability":0.1393,"both_teams_to_score_probability":0.3526,"upset_risk_probability":0.1723,"probability_extra_time":0.1926,"home_advance_probability":0.8277,"away_advance_probability":0.1723,"home_advance_in_90_probability":0.7184,"away_advance_in_90_probability":0.089,"home_advance_after_extra_time_probability":0.0443,"away_advance_after_extra_time_probability":0.0289,"home_advance_on_penalties_probability":0.065,"away_advance_on_penalties_probability":0.0544,"favorite_team_id":"spain","favorite_team":"Spain","favorite_win_probability":0.8277,"projected_advancing_team":"Spain","matchUncertainty":"Low","uncertainty_label":"Low","top_scorelines":[{"scoreline":"1-0","home_goals":1,"away_goals":0,"probability":0.1621},{"scoreline":"2-0","home_goals":2,"away_goals":0,"probability":0.1598},{"scoreline":"3-0","home_goals":3,"away_goals":0,"probability":0.105},{"scoreline":"1-1","home_goals":1,"away_goals":1,"probability":0.0855},{"scoreline":"2-1","home_goals":2,"away_goals":1,"probability":0.0842},{"scoreline":"0-0","home_goals":0,"away_goals":0,"probability":0.0823}],"top_scoreline":"1-0","data_quality_flags":["score_prediction_qf_v1","completed_r16_only","ownership_not_used_as_signal","final_squads_not_source_backed"]},{"prediction_id":"fwc2026-m099-score-qf-v1","match_id":"fwc2026-m099","fixture_id":"fwc2026-m099","match_number":99,"matchday":"QF","fantasy_matchday_id":"qf","stage":"quarterfinal","group":"QF","date":"2026-07-11T22:00:00+01:00","eastern_datetime_label":"Jul 11, 2026 · 5:00 PM ET","fixture_authority_status":"final_known","public_label":"Final","home_team_id":"norway","home_team":"Norway","away_team_id":"england","away_team":"England","home_expected_goals":0.689,"away_expected_goals":1.7,"home_projected_xg":0.689,"away_projected_xg":1.7,"total_expected_goals":2.389,"home_win_probability":0.1477,"draw_probability":0.235,"away_win_probability":0.6173,"home_clean_sheet_probability":0.1827,"away_clean_sheet_probability":0.5021,"both_teams_to_score_probability":0.407,"upset_risk_probability":0.2517,"probability_extra_time":0.235,"home_advance_probability":0.2517,"away_advance_probability":0.7483,"home_advance_in_90_probability":0.1477,"away_advance_in_90_probability":0.6173,"home_advance_after_extra_time_probability":0.0367,"away_advance_after_extra_time_probability":0.0527,"home_advance_on_penalties_probability":0.0674,"away_advance_on_penalties_probability":0.0784,"favorite_team_id":"england","favorite_team":"England","favorite_win_probability":0.7483,"projected_advancing_team":"England","matchUncertainty":"Low","uncertainty_label":"Low","top_scorelines":[{"scoreline":"0-1","home_goals":0,"away_goals":1,"probability":0.1559},{"scoreline":"0-2","home_goals":0,"away_goals":2,"probability":0.1325},{"scoreline":"1-1","home_goals":1,"away_goals":1,"probability":0.1074},{"scoreline":"0-0","home_goals":0,"away_goals":0,"probability":0.0917},{"scoreline":"1-2","home_goals":1,"away_goals":2,"probability":0.0913},{"scoreline":"0-3","home_goals":0,"away_goals":3,"probability":0.0751}],"top_scoreline":"0-1","data_quality_flags":["score_prediction_qf_v1","completed_r16_only","ownership_not_used_as_signal","final_squads_not_source_backed"]},{"prediction_id":"fwc2026-m100-score-qf-v1","match_id":"fwc2026-m100","fixture_id":"fwc2026-m100","match_number":100,"matchday":"QF","fantasy_matchday_id":"qf","stage":"quarterfinal","group":"QF","date":"2026-07-12T02:00:00+01:00","eastern_datetime_label":"Jul 11, 2026 · 9:00 PM ET","fixture_authority_status":"final_known","public_label":"Final","home_team_id":"argentina","home_team":"Argentina","away_team_id":"switzerland","away_team":"Switzerland","home_expected_goals":2.107,"away_expected_goals":0.35,"home_projected_xg":2.107,"away_projected_xg":0.35,"total_expected_goals":2.457,"home_win_probability":0.7884,"draw_probability":0.1616,"away_win_probability":0.05,"home_clean_sheet_probability":0.7047,"away_clean_sheet_probability":0.1216,"both_teams_to_score_probability":0.2594,"upset_risk_probability":0.1178,"probability_extra_time":0.1616,"home_advance_probability":0.8822,"away_advance_probability":0.1178,"home_advance_in_90_probability":0.7884,"away_advance_in_90_probability":0.05,"home_advance_after_extra_time_probability":0.0381,"away_advance_after_extra_time_probability":0.0233,"home_advance_on_penalties_probability":0.0557,"away_advance_on_penalties_probability":0.0445,"favorite_team_id":"argentina","favorite_team":"Argentina","favorite_win_probability":0.8822,"projected_advancing_team":"Argentina","matchUncertainty":"Low","uncertainty_label":"Low","top_scorelines":[{"scoreline":"2-0","home_goals":2,"away_goals":0,"probability":0.1903},{"scoreline":"1-0","home_goals":1,"away_goals":0,"probability":0.1806},{"scoreline":"3-0","home_goals":3,"away_goals":0,"probability":0.1336},{"scoreline":"0-0","home_goals":0,"away_goals":0,"probability":0.0857},{"scoreline":"4-0","home_goals":4,"away_goals":0,"probability":0.0704},{"scoreline":"2-1","home_goals":2,"away_goals":1,"probability":0.0666}],"top_scoreline":"2-0","data_quality_flags":["score_prediction_qf_v1","completed_r16_only","ownership_not_used_as_signal","final_squads_not_source_backed"]}],"teamFixturePredictions":[{"fixture_id":"fwc2026-m097","match_number":97,"team_id":"france","team":"France","opponent_team_id":"morocco","opponent":"Morocco","side":"home_listed","expected_goals":1.809,"expected_goals_against":0.35,"win_probability":0.7347,"draw_probability":0.201,"loss_probability":0.0644,"clean_sheet_probability":0.7047,"advance_probability":0.8494},{"fixture_id":"fwc2026-m097","match_number":97,"team_id":"morocco","team":"Morocco","opponent_team_id":"france","opponent":"France","side":"away_listed","expected_goals":0.35,"expected_goals_against":1.809,"win_probability":0.0644,"draw_probability":0.201,"loss_probability":0.7347,"clean_sheet_probability":0.1638,"advance_probability":0.1506},{"fixture_id":"fwc2026-m098","match_number":98,"team_id":"spain","team":"Spain","opponent_team_id":"belgium","opponent":"Belgium","side":"home_listed","expected_goals":1.971,"expected_goals_against":0.527,"win_probability":0.7184,"draw_probability":0.1926,"loss_probability":0.089,"clean_sheet_probability":0.5904,"advance_probability":0.8277},{"fixture_id":"fwc2026-m098","match_number":98,"team_id":"belgium","team":"Belgium","opponent_team_id":"spain","opponent":"Spain","side":"away_listed","expected_goals":0.527,"expected_goals_against":1.971,"win_probability":0.089,"draw_probability":0.1926,"loss_probability":0.7184,"clean_sheet_probability":0.1393,"advance_probability":0.1723},{"fixture_id":"fwc2026-m099","match_number":99,"team_id":"norway","team":"Norway","opponent_team_id":"england","opponent":"England","side":"home_listed","expected_goals":0.689,"expected_goals_against":1.7,"win_probability":0.1477,"draw_probability":0.235,"loss_probability":0.6173,"clean_sheet_probability":0.1827,"advance_probability":0.2517},{"fixture_id":"fwc2026-m099","match_number":99,"team_id":"england","team":"England","opponent_team_id":"norway","opponent":"Norway","side":"away_listed","expected_goals":1.7,"expected_goals_against":0.689,"win_probability":0.6173,"draw_probability":0.235,"loss_probability":0.1477,"clean_sheet_probability":0.5021,"advance_probability":0.7483},{"fixture_id":"fwc2026-m100","match_number":100,"team_id":"argentina","team":"Argentina","opponent_team_id":"switzerland","opponent":"Switzerland","side":"home_listed","expected_goals":2.107,"expected_goals_against":0.35,"win_probability":0.7884,"draw_probability":0.1616,"loss_probability":0.05,"clean_sheet_probability":0.7047,"advance_probability":0.8822},{"fixture_id":"fwc2026-m100","match_number":100,"team_id":"switzerland","team":"Switzerland","opponent_team_id":"argentina","opponent":"Argentina","side":"away_listed","expected_goals":0.35,"expected_goals_against":2.107,"win_probability":0.05,"draw_probability":0.1616,"loss_probability":0.7884,"clean_sheet_probability":0.1216,"advance_probability":0.1178}],"defaultMatchday":"qf"}
