{
  "schema_version": "team_builder_sf_validation_v1",
  "generated_at": "2026-07-12T12:43:21.500Z",
  "status": "pass",
  "summary": {
    "projection_rows": 100,
    "builder_eligible_rows": 29,
    "recommendation_rows": 125,
    "by_position": {
      "DEF": 14,
      "FWD": 4,
      "GK": 3,
      "MID": 8
    },
    "balanced_by_position": {
      "GK": 2,
      "DEF": 5,
      "MID": 5,
      "FWD": 3
    },
    "defaultMatchday": "sf",
    "balanced_projected_points": 61.36,
    "greedy_projected_points": 62.99,
    "balanced_vs_greedy_delta": -1.63,
    "path_value_to_final_third_place_included": true,
    "role_volatility_included": true,
    "explicit_qf_starters_only_for_builder_samples": true,
    "points_only_rows_used_as_starters": 0,
    "eliminated_and_unavailable_excluded": true
  },
  "balanced_squad": [
    {
      "name": "Unai Simón",
      "country": "Spain",
      "position": "GK",
      "points": 4.163,
      "opponent": "France",
      "start_probability": 0.885,
      "lineupEvidenceType": "explicit_qf_starter",
      "qfStarted": true,
      "role_caution": null,
      "coreEligibilityReason": "explicit_qf_starter_with_sf_role_confidence"
    },
    {
      "name": "Emiliano Martínez",
      "country": "Argentina",
      "position": "GK",
      "points": 3.848,
      "opponent": "England",
      "start_probability": 0.88,
      "lineupEvidenceType": "explicit_qf_starter",
      "qfStarted": true,
      "role_caution": null,
      "coreEligibilityReason": "explicit_qf_starter_with_sf_role_confidence"
    },
    {
      "name": "Lisandro Martínez",
      "country": "Argentina",
      "position": "DEF",
      "points": 4.565,
      "opponent": "England",
      "start_probability": 0.88,
      "lineupEvidenceType": "explicit_qf_starter",
      "qfStarted": true,
      "role_caution": null,
      "coreEligibilityReason": "explicit_qf_starter_with_sf_role_confidence"
    },
    {
      "name": "Aymeric Laporte",
      "country": "Spain",
      "position": "DEF",
      "points": 4.58,
      "opponent": "France",
      "start_probability": 0.881,
      "lineupEvidenceType": "explicit_qf_starter",
      "qfStarted": true,
      "role_caution": null,
      "coreEligibilityReason": "explicit_qf_starter_with_sf_role_confidence"
    },
    {
      "name": "Marc Cucurella",
      "country": "Spain",
      "position": "DEF",
      "points": 4.572,
      "opponent": "France",
      "start_probability": 0.883,
      "lineupEvidenceType": "explicit_qf_starter",
      "qfStarted": true,
      "role_caution": null,
      "coreEligibilityReason": "explicit_qf_starter_with_sf_role_confidence"
    },
    {
      "name": "Pau Cubarsí",
      "country": "Spain",
      "position": "DEF",
      "points": 4.541,
      "opponent": "France",
      "start_probability": 0.878,
      "lineupEvidenceType": "explicit_qf_starter",
      "qfStarted": true,
      "role_caution": null,
      "coreEligibilityReason": "explicit_qf_starter_with_sf_role_confidence"
    },
    {
      "name": "Cristian Romero",
      "country": "Argentina",
      "position": "DEF",
      "points": 4.095,
      "opponent": "England",
      "start_probability": 0.88,
      "lineupEvidenceType": "explicit_qf_starter",
      "qfStarted": true,
      "role_caution": null,
      "coreEligibilityReason": "explicit_qf_starter_with_sf_role_confidence"
    },
    {
      "name": "Alexis Mac Allister",
      "country": "Argentina",
      "position": "MID",
      "points": 3.736,
      "opponent": "England",
      "start_probability": 0.88,
      "lineupEvidenceType": "explicit_qf_starter",
      "qfStarted": true,
      "role_caution": null,
      "coreEligibilityReason": "explicit_qf_starter_with_sf_role_confidence"
    },
    {
      "name": "Rodrigo De Paul",
      "country": "Argentina",
      "position": "MID",
      "points": 3.667,
      "opponent": "England",
      "start_probability": 0.88,
      "lineupEvidenceType": "explicit_qf_starter",
      "qfStarted": true,
      "role_caution": null,
      "coreEligibilityReason": "explicit_qf_starter_with_sf_role_confidence"
    },
    {
      "name": "Ousmane Dembélé",
      "country": "France",
      "position": "MID",
      "points": 3.756,
      "opponent": "Spain",
      "start_probability": 0.878,
      "lineupEvidenceType": "explicit_qf_starter",
      "qfStarted": true,
      "role_caution": null,
      "coreEligibilityReason": "explicit_qf_starter_with_sf_role_confidence"
    },
    {
      "name": "Lamine Yamal Nasraoui Ebana",
      "country": "Spain",
      "position": "MID",
      "points": 3.553,
      "opponent": "France",
      "start_probability": 0.878,
      "lineupEvidenceType": "explicit_qf_starter",
      "qfStarted": true,
      "role_caution": null,
      "coreEligibilityReason": "explicit_qf_starter_with_sf_role_confidence"
    },
    {
      "name": "Rodrigo Hernández Cascante",
      "country": "Spain",
      "position": "MID",
      "points": 3.514,
      "opponent": "France",
      "start_probability": 0.878,
      "lineupEvidenceType": "explicit_qf_starter",
      "qfStarted": true,
      "role_caution": null,
      "coreEligibilityReason": "explicit_qf_starter_with_sf_role_confidence"
    },
    {
      "name": "Lionel Messi",
      "country": "Argentina",
      "position": "FWD",
      "points": 4.369,
      "opponent": "England",
      "start_probability": 0.88,
      "lineupEvidenceType": "explicit_qf_starter",
      "qfStarted": true,
      "role_caution": null,
      "coreEligibilityReason": "explicit_qf_starter_with_sf_role_confidence"
    },
    {
      "name": "Mikel Oyarzabal",
      "country": "Spain",
      "position": "FWD",
      "points": 4.378,
      "opponent": "France",
      "start_probability": 0.878,
      "lineupEvidenceType": "explicit_qf_starter",
      "qfStarted": true,
      "role_caution": null,
      "coreEligibilityReason": "explicit_qf_starter_with_sf_role_confidence"
    },
    {
      "name": "Kylian Mbappé",
      "country": "France",
      "position": "FWD",
      "points": 4.022,
      "opponent": "Spain",
      "start_probability": 0.883,
      "lineupEvidenceType": "explicit_qf_starter",
      "qfStarted": true,
      "role_caution": null,
      "coreEligibilityReason": "explicit_qf_starter_with_sf_role_confidence"
    }
  ],
  "errors": []
}
